lonelyconnect/__init__.py
lonelyconnect/auth.py
lonelyconnect/game.py
lonelyconnect/models.py
lonelyconnect/route_ui.py
lonelyconnect-0.1.0.dist-info/entry_points.txt
lonelyconnect-0.1.0.dist-info/WHEEL
lonelyconnect-0.1.0.dist-info/METADATA
lonelyconnect-0.1.0.dist-info/RECORD
