Metadata-Version: 2.1
Name: lonelyconnect
Version: 0.1.0
Summary: Make your own OnlyConnect-style quizzes at home
Home-page: https://github.com/L3viathan/lonelyconnect
Author: L3viathan
Author-email: git@l3vi.de
Requires-Python: >=3.9,<4.0
Classifier: Environment :: Web Environment
Classifier: Operating System :: OS Independent
Classifier: Programming Language :: Python :: 3
Classifier: Programming Language :: Python :: 3.9
Classifier: Topic :: Games/Entertainment :: Puzzle Games
Requires-Dist: Jinja2 (>=3.0.1,<4.0.0)
Requires-Dist: MarkupSafe (>=2.0.1,<3.0.0)
Requires-Dist: PyYAML (>=5.4.1,<6.0.0)
Requires-Dist: aiofiles (>=0.7.0,<0.8.0)
Requires-Dist: fastapi (>=0.68.0,<0.69.0)
Requires-Dist: python-multipart (>=0.0.5,<0.0.6)
Requires-Dist: uvicorn (>=0.15.0,<0.16.0)
Project-URL: Repository, https://github.com/L3viathan/lonelyconnect
